LICENSE.txt
quantstats/__init__.py
quantstats/_plotting/__init__.py
quantstats/_plotting/core.py
quantstats/_plotting/wrappers.py
quantstats/plots.py
quantstats/report.html
quantstats/reports.py
quantstats/stats.py
quantstats/utils.py
quantstats/version.py
quantstats_reloaded-0.1.0.dist-info/LICENSE.txt
quantstats_reloaded-0.1.0.dist-info/METADATA
quantstats_reloaded-0.1.0.dist-info/WHEEL
quantstats_reloaded-0.1.0.dist-info/RECORD
