Metadata-Version: 2.1
Name: quantstats-reloaded
Version: 0.1.0
Summary: Portfolio analytics for quants
Home-page: https://github.com/zillionare/quantstats-reloaded
License: Apache Software License
Keywords: quant,algotrading,algorithmic-trading,quantitative-trading,quantitative-analysis,algo-trading,visualization,plotting
Author: Aaron Yang
Author-email: aaron_yang@jieyu.ai
Requires-Python: >=3.10,<4.0
Classifier: Development Status :: 5 - Production/Stable
Classifier: Intended Audience :: Developers
Classifier: Intended Audience :: Financial and Insurance Industry
Classifier: Intended Audience :: Science/Research
Classifier: License :: OSI Approved :: Apache Software License
Classifier: License :: Other/Proprietary License
Classifier: Operating System :: OS Independent
Classifier: Programming Language :: Python :: 3
Classifier: Programming Language :: Python :: 3.10
Classifier: Programming Language :: Python :: 3.11
Classifier: Programming Language :: Python :: 3.10
Classifier: Programming Language :: Python :: 3.11
Classifier: Programming Language :: Python :: 3.12
Classifier: Topic :: Office/Business :: Financial
Classifier: Topic :: Office/Business :: Financial :: Investment
Classifier: Topic :: Scientific/Engineering
Classifier: Topic :: Scientific/Engineering :: Information Analysis
Classifier: Topic :: Scientific/Engineering :: Mathematics
Classifier: Topic :: Software Development :: Libraries
Classifier: Topic :: Software Development :: Libraries :: Python Modules
Requires-Dist: matplotlib (>=3.0.0)
Requires-Dist: numpy (>=1.16.5)
Requires-Dist: pandas (>=0.24.0)
Requires-Dist: scipy (>=1.2.0)
Requires-Dist: seaborn (>=0.9.0)
Requires-Dist: tabulate (>=0.8.0)
Project-URL: Repository, https://github.com/zillionare/quantstats-reloaded
